<?xml version="1.0" encoding="utf-8" ?><dwsync><file name="jewelry.png" server="atmanagement-japan.com/ssl/home/" local="3606002107" remote="3606084420" Dst="-1" /><file name="product_step_pc@2x.png" server="atmanagement-japan.com/ssl/home/" local="3606002107" remote="3606084420" Dst="-1" /><file name="furniture@2x.png" server="atmanagement-japan.com/ssl/home/" local="3606002107" remote="3606084420" Dst="-1" /><file name="zaiko_genkin@2x.png" server="atmanagement-japan.com/ssl/home/" local="3606002107" remote="3606084420" Dst="-1" /><file name="zaiko_genkinka_sm.jpg" server="atmanagement-japan.com/ssl/home/" local="3606002107" remote="3606084420" Dst="-1" /><file name="zaiko_kokoroatari.png" server="atmanagement-japan.com/ssl/home/" local="3606002107" remote="3606084420" Dst="-1" /><file name="zaiko_kokoroatari.jpg" server="atmanagement-japan.com/ssl/home/" local="3606002107" remote="3606084420" Dst="-1" /><file name="zaiko_genkinka.jpg" server="atmanagement-japan.com/ssl/home/" local="3606002107" remote="3606084420" Dst="-1" /><file name="zaiko_genkinka_sm@2x.jpg" server="atmanagement-japan.com/ssl/home/" local="3606002107" remote="3606084420" Dst="-1" /><file name="product_step_sm2@2x.png" server="atmanagement-japan.com/ssl/home/" local="3606002107" remote="3606084420" Dst="-1" /><file name="zaiko_image.png" server="atmanagement-japan.com/ssl/home/" local="3606002107" remote="3606084420" Dst="-1" /><file name="electronics@2x.png" server="atmanagement-japan.com/ssl/home/" local="3606002107" remote="3606084420" Dst="-1" /><file name="zaiko_riyousuruto.jpg" server="atmanagement-japan.com/ssl/home/" local="3606002107" remote="3606084420" Dst="-1" /><file name="product_step_sm4.png" server="atmanagement-japan.com/ssl/home/" local="3606002107" remote="3606084420" Dst="-1" /><file name="apparel.png" server="atmanagement-japan.com/ssl/home/" local="3606002107" remote="3606084420" Dst="-1" /><file name="zaiko_kokoroatari_sm@2x.jpg" server="atmanagement-japan.com/ssl/home/" local="3606002107" remote="3606084420" Dst="-1" /><file name="car@2x.png" server="atmanagement-japan.com/ssl/home/" local="3606002107" remote="3606084420" Dst="-1" /><file name="zaiko_riyousuruto_sm.jpg" server="atmanagement-japan.com/ssl/home/" local="3606002107" remote="3606084420" Dst="-1" /><file name="product_step_sm1.png" server="atmanagement-japan.com/ssl/home/" local="3606002107" remote="3606084420" Dst="-1" /><file name="product_step_sm4@2x.png" server="atmanagement-japan.com/ssl/home/" local="3606002107" remote="3606084420" Dst="-1" /><file name="zaiko_nagare@2x.jpg" server="atmanagement-japan.com/ssl/home/" local="3606002107" remote="3606084420" Dst="-1" /><file name="product_step_sm2.png" server="atmanagement-japan.com/ssl/home/" local="3606002107" remote="3606084420" Dst="-1" /><file name="product_step_sm3.png" server="atmanagement-japan.com/ssl/home/" local="3606002107" remote="3606084420" Dst="-1" /><file name="zaiko_kokoroatari@2x.png" server="atmanagement-japan.com/ssl/home/" local="3606002107" remote="3606084420" Dst="-1" /><file name="zaiko_kokoroatari@2x.jpg" server="atmanagement-japan.com/ssl/home/" local="3606002107" remote="3606084420" Dst="-1" /><file name="product_step_pc.png" server="atmanagement-japan.com/ssl/home/" local="3606002107" remote="3606084420" Dst="-1" /><file name="apparel@2x.png" server="atmanagement-japan.com/ssl/home/" local="3606002107" remote="3606084420" Dst="-1" /><file name="office@2x.png" server="atmanagement-japan.com/ssl/home/" local="3606002107" remote="3606084420" Dst="-1" /><file name="electronics.png" server="atmanagement-japan.com/ssl/home/" local="3606002107" remote="3606084420" Dst="-1" /><file name="product_step_sm1@2x.png" server="atmanagement-japan.com/ssl/home/" local="3606002107" remote="3606084420" Dst="-1" /><file name="office.png" server="atmanagement-japan.com/ssl/home/" local="3606002107" remote="3606084420" Dst="-1" /><file name="zaiko_genkin.png" server="atmanagement-japan.com/ssl/home/" local="3606002107" remote="3606084420" Dst="-1" /><file name="zaiko_riyousuruto_sm@2x.jpg" server="atmanagement-japan.com/ssl/home/" local="3606002107" remote="3606084480" Dst="-1" /><file name="zaiko_riyousuruto@2x.jpg" server="atmanagement-japan.com/ssl/home/" local="3606002107" remote="3606084480" Dst="-1" /><file name="zaiko_nagare_sm.jpg" server="atmanagement-japan.com/ssl/home/" local="3606002107" remote="3606084480" Dst="-1" /><file name="product_step_sm3@2x.png" server="atmanagement-japan.com/ssl/home/" local="3606002107" remote="3606084480" Dst="-1" /><file name="car.png" server="atmanagement-japan.com/ssl/home/" local="3606002107" remote="3606084480" Dst="-1" /><file name="jewelry@2x.png" server="atmanagement-japan.com/ssl/home/" local="3606002107" remote="3606084480" Dst="-1" /><file name="zaiko_kokoroatari_sm.jpg" server="atmanagement-japan.com/ssl/home/" local="3606002107" remote="3606084480" Dst="-1" /><file name="zaiko_kaitori.jpg" server="atmanagement-japan.com/ssl/home/" local="3606002107" remote="3606084480" Dst="-1" /><file name="zaiko_kaitori@2x.jpg" server="atmanagement-japan.com/ssl/home/" local="3606002107" remote="3606084480" Dst="-1" /><file name="zaiko_genkinka@2x.jpg" server="atmanagement-japan.com/ssl/home/" local="3606002107" remote="3606084480" Dst="-1" /><file name="zaiko_image@2x.png" server="atmanagement-japan.com/ssl/home/" local="3606002107" remote="3606084480" Dst="-1" /><file name="zaiko_nagare.jpg" server="atmanagement-japan.com/ssl/home/" local="3606002107" remote="3606084480" Dst="-1" /><file name="furniture.png" server="atmanagement-japan.com/ssl/home/" local="3606002107" remote="3606084480" Dst="-1" /><file name="zaiko_nagare_sm@2x.jpg" server="atmanagement-japan.com/ssl/home/" local="3606002107" remote="3606084480" Dst="-1" /></dwsync>